parzenwindow/__init__.py
parzenwindow/pdf_estimate.py
parzen_windows-0.0.4.dist-info/METADATA
parzen_windows-0.0.4.dist-info/WHEEL
parzen_windows-0.0.4.dist-info/top_level.txt
parzen_windows-0.0.4.dist-info/RECORD
