Metadata-Version: 2.1
Name: parzen-windows
Version: 0.0.4
Summary: Making pdf estimates as seamless as possible
Author-email: Ian Meyer <imeyer@unomaha.edu>
Project-URL: Homepage, https://github.com/imeyer2/parzen-windows
Requires-Python: >=3.8
